django_bitly/__init__.py
django_bitly/conf.py
django_bitly/exceptions.py
django_bitly/models.py
django_bitly/views.py
django_bitly/migrations/0001_initial.py
django_bitly/migrations/__init__.py
django_bitly/templatetags/__init__.py
django_bitly/templatetags/bitly.py
django_bitly-1.2.1.dist-info/AUTHORS
django_bitly-1.2.1.dist-info/LICENSE.txt
django_bitly-1.2.1.dist-info/METADATA
django_bitly-1.2.1.dist-info/WHEEL
django_bitly-1.2.1.dist-info/top_level.txt
django_bitly-1.2.1.dist-info/RECORD
